__init__.py
test/__init__.py
test/cli/__init__.py
test/cli/commands.py
test/cli/test_filerenamer.py
test/cli/test_gitbook.py
test/cli/test_googledrive.py
test/cli/test_googlesearch.py
test/cli/test_theme.py
test/core/__init__.py
test/core/test_common.py
test/core/test_markdown.py
test/model/__init__.py
test/model/test_filesystem.py
test/model/test_input.py
test/model/test_markdown.py
ypackage/__init__.py
ypackage/cli/__init__.py
ypackage/cli/common.py
ypackage/cli/filesystem.py
ypackage/cli/gdrive.py
ypackage/cli/gitbook.py
ypackage/cli/gsearch.py
ypackage/cli/theme.py
ypackage/core/__init__.py
ypackage/core/background.py
ypackage/core/common.py
ypackage/core/filesystem.py
ypackage/core/gitbook.py
ypackage/core/github.py
ypackage/core/input.py
ypackage/core/markdown.py
ypackage/core/theme.py
ypackage/model/__init__.py
ypackage/model/common.py
ypackage/model/filesystem.py
ypackage/model/gitbook.py
ypackage/model/input.py
ypackage/model/markdown.py
ypackage/model/theme.py
ypackage-3.0.4.dist-info/LICENSE
ypackage-3.0.4.dist-info/METADATA
ypackage-3.0.4.dist-info/WHEEL
ypackage-3.0.4.dist-info/entry_points.txt
ypackage-3.0.4.dist-info/top_level.txt
ypackage-3.0.4.dist-info/RECORD
