Metadata-Version: 2.1
Name: ypackage
Version: 3.0.4
Summary: Yunus Emre Ak ~ YEmreAk (@yedhrab)'ın google drive direkt link oluşturmagitbook entegrasyonu, google arama motoru sonuçlarını filtreleme ile ilgili çalışmaları 
Home-page: https://github.com/yedhrab/YPackage
Author: Yunus Emre Ak
Author-email: yemreak.com@gmail.com
License: Apache Software License 2.0
Project-URL: Changelog, https://github.com/yedhrab/YPackage/blob/master/docs/CHANGELOG.md
Project-URL: Issue Tracker, https://github.com/yedhrab/YPackage/issues
Keywords: ypackage,yedhrab,yemreak,gitbook,github,google-search,google,link,drive,renamer,bulk
Platform: UNKNOWN
Classifier: Development Status :: 5 - Production/Stable
Classifier: Intended Audience :: Developers
Classifier: License :: OSI Approved :: BSD License
Classifier: Operating System :: Unix
Classifier: Operating System :: POSIX
Classifier: Operating System :: Microsoft :: Windows
Classifier: Programming Language :: Python
Classifier: Programming Language :: Python :: 2.7
Classifier: Programming Language :: Python :: 3
Classifier: Programming Language :: Python :: 3.5
Classifier: Programming Language :: Python :: 3.6
Classifier: Programming Language :: Python :: 3.7
Classifier: Programming Language :: Python :: 3.8
Classifier: Programming Language :: Python :: Implementation :: CPython
Classifier: Programming Language :: Python :: Implementation :: PyPy
Classifier: Topic :: Utilities
Requires-Python: >=3
License-File: LICENSE
Requires-Dist: google (==3.0.0)
Requires-Dist: requests (==2.27.1)
Requires-Dist: PyDriller (==2.0)
Requires-Dist: coloredlogs (==15.0.1)
Requires-Dist: keyboard (==0.13.5)
Requires-Dist: mouse (==0.7.1)
